{
  "annotations": {
    "list": [
      {
        "builtIn": 1,
        "datasource": {
          "type": "grafana",
          "uid": "-- Grafana --"
        },
        "enable": true,
        "hide": true,
        "iconColor": "rgba(0, 211, 255, 1)",
        "name": "Annotations & Alerts",
        "target": {
          "limit": 100,
          "matchAny": false,
          "tags": [],
          "type": "dashboard"
        },
        "type": "dashboard"
      }
    ]
  },
  "editable": true,
  "fiscalYearStartMonth": 0,
  "graphTooltip": 0,
  "links": [],
  "liveNow": false,
  "panels": [
    {
      "collapsed": false,
      "gridPos": {
        "h": 1,
        "w": 24,
        "x": 0,
        "y": 0
      },
      "id": 6,
      "panels": [],
      "title": "Dane aktualne ",
      "type": "row"
    },
    {
      "datasource": {
        "type": "influxdb",
        "uid": "P951FEA4DE68E13C5"
      },
      "description": "",
      "fieldConfig": {
        "defaults": {
          "color": {
            "fixedColor": "orange",
            "mode": "fixed"
          },
          "mappings": [],
          "max": 50,
          "min": 0,
          "thresholds": {
            "mode": "absolute",
            "steps": [
              {
                "color": "green",
                "value": null
              },
              {
                "color": "red",
                "value": 80
              }
            ]
          },
          "unit": "celsius"
        },
        "overrides": []
      },
      "gridPos": {
        "h": 8,
        "w": 8,
        "x": 0,
        "y": 1
      },
      "id": 2,
      "options": {
        "orientation": "auto",
        "reduceOptions": {
          "calcs": [
            "lastNotNull"
          ],
          "fields": "",
          "values": false
        },
        "showThresholdLabels": false,
        "showThresholdMarkers": true
      },
      "pluginVersion": "9.3.0-beta1",
      "targets": [
        {
          "datasource": {
            "type": "influxdb",
            "uid": "P951FEA4DE68E13C5"
          },
          "query": "from(bucket: \"pi\")\n  |> range(start: v.timeRangeStart, stop: v.timeRangeStop)\n  |> filter(fn: (r) => r[\"_measurement\"] == \"mem\")\n  |> filter(fn: (r) => r[\"_field\"] == \"temperature\")\n  |> filter(fn: (r) => r[\"host\"] == \"pi\")\n  |> aggregateWindow(every: v.windowPeriod, fn: last, createEmpty: false)\n  |> yield(name: \"last\")",
          "refId": "A"
        }
      ],
      "title": "Temperatura",
      "type": "gauge"
    },
    {
      "datasource": {
        "type": "influxdb",
        "uid": "P951FEA4DE68E13C5"
      },
      "description": "",
      "fieldConfig": {
        "defaults": {
          "color": {
            "fixedColor": "purple",
            "mode": "fixed"
          },
          "mappings": [],
          "max": 50,
          "min": 0,
          "thresholds": {
            "mode": "absolute",
            "steps": [
              {
                "color": "green",
                "value": null
              },
              {
                "color": "red",
                "value": 50
              }
            ]
          },
          "unit": "percent"
        },
        "overrides": []
      },
      "gridPos": {
        "h": 8,
        "w": 8,
        "x": 8,
        "y": 1
      },
      "id": 3,
      "options": {
        "orientation": "auto",
        "reduceOptions": {
          "calcs": [
            "lastNotNull"
          ],
          "fields": "",
          "values": false
        },
        "showThresholdLabels": false,
        "showThresholdMarkers": true
      },
      "pluginVersion": "9.3.0-beta1",
      "targets": [
        {
          "datasource": {
            "type": "influxdb",
            "uid": "P951FEA4DE68E13C5"
          },
          "query": "from(bucket: \"pi\")\n  |> range(start: v.timeRangeStart, stop: v.timeRangeStop)\n  |> filter(fn: (r) => r[\"_measurement\"] == \"mem\")\n  |> filter(fn: (r) => r[\"_field\"] == \"humidity\")\n  |> filter(fn: (r) => r[\"host\"] == \"pi\")\n  |> aggregateWindow(every: v.windowPeriod, fn: last, createEmpty: false)\n  |> yield(name: \"last\")",
          "refId": "A"
        }
      ],
      "title": "Wilgotność",
      "type": "gauge"
    },
    {
      "datasource": {
        "type": "influxdb",
        "uid": "P951FEA4DE68E13C5"
      },
      "description": "",
      "fieldConfig": {
        "defaults": {
          "color": {
            "fixedColor": "green",
            "mode": "fixed"
          },
          "decimals": 0,
          "mappings": [],
          "max": 1100,
          "min": 900,
          "noValue": "No data",
          "thresholds": {
            "mode": "absolute",
            "steps": [
              {
                "color": "green",
                "value": null
              },
              {
                "color": "red",
                "value": 50
              }
            ]
          },
          "unit": "pressurehpa"
        },
        "overrides": []
      },
      "gridPos": {
        "h": 8,
        "w": 8,
        "x": 16,
        "y": 1
      },
      "id": 4,
      "options": {
        "orientation": "auto",
        "reduceOptions": {
          "calcs": [
            "lastNotNull"
          ],
          "fields": "",
          "values": false
        },
        "showThresholdLabels": false,
        "showThresholdMarkers": true
      },
      "pluginVersion": "9.3.0-beta1",
      "targets": [
        {
          "datasource": {
            "type": "influxdb",
            "uid": "P951FEA4DE68E13C5"
          },
          "query": "from(bucket: \"pi\")\n  |> range(start: v.timeRangeStart, stop: v.timeRangeStop)\n  |> filter(fn: (r) => r[\"_measurement\"] == \"mem\")\n  |> filter(fn: (r) => r[\"_field\"] == \"pressure\")\n  |> filter(fn: (r) => r[\"host\"] == \"pi\")\n  |> aggregateWindow(every: v.windowPeriod, fn: last, createEmpty: false)\n  |> yield(name: \"last\")",
          "refId": "A"
        }
      ],
      "title": "Ciśnienie",
      "type": "gauge"
    },
    {
      "datasource": {
        "type": "influxdb",
        "uid": "P951FEA4DE68E13C5"
      },
      "description": "",
      "fieldConfig": {
        "defaults": {
          "color": {
            "fixedColor": "orange",
            "mode": "fixed"
          },
          "custom": {
            "axisCenteredZero": false,
            "axisColorMode": "text",
            "axisLabel": "",
            "axisPlacement": "auto",
            "axisSoftMax": 25,
            "axisSoftMin": 20,
            "barAlignment": 0,
            "drawStyle": "line",
            "fillOpacity": 0,
            "gradientMode": "none",
            "hideFrom": {
              "legend": false,
              "tooltip": false,
              "viz": false
            },
            "lineInterpolation": "linear",
            "lineStyle": {
              "fill": "solid"
            },
            "lineWidth": 1,
            "pointSize": 5,
            "scaleDistribution": {
              "type": "linear"
            },
            "showPoints": "auto",
            "spanNulls": true,
            "stacking": {
              "group": "A",
              "mode": "none"
            },
            "thresholdsStyle": {
              "mode": "off"
            }
          },
          "mappings": [],
          "thresholds": {
            "mode": "absolute",
            "steps": [
              {
                "color": "green",
                "value": null
              },
              {
                "color": "red",
                "value": 80
              }
            ]
          },
          "unit": "celsius"
        },
        "overrides": []
      },
      "gridPos": {
        "h": 10,
        "w": 8,
        "x": 0,
        "y": 9
      },
      "id": 8,
      "options": {
        "legend": {
          "calcs": [],
          "displayMode": "list",
          "placement": "bottom",
          "showLegend": false
        },
        "tooltip": {
          "mode": "single",
          "sort": "none"
        }
      },
      "pluginVersion": "9.3.0-beta1",
      "targets": [
        {
          "datasource": {
            "type": "influxdb",
            "uid": "P951FEA4DE68E13C5"
          },
          "query": "from(bucket: \"pi/autogen\")\n  |> range(start: v.timeRangeStart, stop: v.timeRangeStop)\n  |> filter(fn: (r) => r._measurement == \"mem\" and r._field == \"temperature\")\n  |> aggregateWindow(every: v.windowPeriod, fn: max)\n\n",
          "refId": "A"
        }
      ],
      "title": "Temperatura",
      "type": "timeseries"
    },
    {
      "datasource": {
        "type": "influxdb",
        "uid": "P951FEA4DE68E13C5"
      },
      "description": "",
      "fieldConfig": {
        "defaults": {
          "color": {
            "fixedColor": "purple",
            "mode": "fixed"
          },
          "custom": {
            "axisCenteredZero": false,
            "axisColorMode": "text",
            "axisLabel": "",
            "axisPlacement": "auto",
            "barAlignment": 0,
            "drawStyle": "line",
            "fillOpacity": 0,
            "gradientMode": "none",
            "hideFrom": {
              "legend": false,
              "tooltip": false,
              "viz": false
            },
            "lineInterpolation": "linear",
            "lineStyle": {
              "fill": "solid"
            },
            "lineWidth": 1,
            "pointSize": 5,
            "scaleDistribution": {
              "type": "linear"
            },
            "showPoints": "auto",
            "spanNulls": false,
            "stacking": {
              "group": "A",
              "mode": "none"
            },
            "thresholdsStyle": {
              "mode": "off"
            }
          },
          "mappings": [],
          "thresholds": {
            "mode": "absolute",
            "steps": [
              {
                "color": "green",
                "value": null
              },
              {
                "color": "red",
                "value": 80
              }
            ]
          },
          "unit": "percent"
        },
        "overrides": []
      },
      "gridPos": {
        "h": 10,
        "w": 8,
        "x": 8,
        "y": 9
      },
      "id": 9,
      "options": {
        "legend": {
          "calcs": [],
          "displayMode": "list",
          "placement": "bottom",
          "showLegend": false
        },
        "tooltip": {
          "mode": "single",
          "sort": "none"
        }
      },
      "pluginVersion": "9.3.0-beta1",
      "targets": [
        {
          "datasource": {
            "type": "influxdb",
            "uid": "P951FEA4DE68E13C5"
          },
          "query": "from(bucket: \"pi/autogen\")\n  |> range(start: v.timeRangeStart, stop: v.timeRangeStop)\n  |> filter(fn: (r) => r._measurement == \"mem\" and r._field == \"humidity\")\n  |> aggregateWindow(every: v.windowPeriod, fn: max)\n",
          "refId": "A"
        }
      ],
      "title": "Wilgotnosc",
      "type": "timeseries"
    },
    {
      "datasource": {
        "type": "influxdb",
        "uid": "P951FEA4DE68E13C5"
      },
      "description": "",
      "fieldConfig": {
        "defaults": {
          "color": {
            "fixedColor": "green",
            "mode": "fixed"
          },
          "custom": {
            "axisCenteredZero": false,
            "axisColorMode": "text",
            "axisLabel": "",
            "axisPlacement": "auto",
            "barAlignment": 0,
            "drawStyle": "line",
            "fillOpacity": 0,
            "gradientMode": "none",
            "hideFrom": {
              "legend": false,
              "tooltip": false,
              "viz": false
            },
            "lineInterpolation": "linear",
            "lineStyle": {
              "fill": "solid"
            },
            "lineWidth": 1,
            "pointSize": 5,
            "scaleDistribution": {
              "type": "linear"
            },
            "showPoints": "auto",
            "spanNulls": false,
            "stacking": {
              "group": "A",
              "mode": "none"
            },
            "thresholdsStyle": {
              "mode": "off"
            }
          },
          "mappings": [],
          "thresholds": {
            "mode": "absolute",
            "steps": [
              {
                "color": "green",
                "value": null
              },
              {
                "color": "red",
                "value": 80
              }
            ]
          },
          "unit": "pressurehpa"
        },
        "overrides": []
      },
      "gridPos": {
        "h": 10,
        "w": 8,
        "x": 16,
        "y": 9
      },
      "id": 10,
      "options": {
        "legend": {
          "calcs": [],
          "displayMode": "list",
          "placement": "bottom",
          "showLegend": false
        },
        "tooltip": {
          "mode": "single",
          "sort": "none"
        }
      },
      "pluginVersion": "9.3.0-beta1",
      "targets": [
        {
          "datasource": {
            "type": "influxdb",
            "uid": "P951FEA4DE68E13C5"
          },
          "query": "from(bucket: \"pi/autogen\")\n  |> range(start: v.timeRangeStart, stop: v.timeRangeStop)\n  |> filter(fn: (r) => r._measurement == \"mem\" and r._field == \"pressure\")\n  |> aggregateWindow(every: v.windowPeriod, fn: max)\n",
          "refId": "A"
        }
      ],
      "title": "Cisnienie",
      "type": "timeseries"
    }
  ],
  "refresh": "5s",
  "schemaVersion": 37,
  "style": "dark",
  "tags": [],
  "templating": {
    "list": []
  },
  "time": {
    "from": "now-24h",
    "to": "now"
  },
  "timepicker": {},
  "timezone": "",
  "title": "Temperature - Pressure - Humidity",
  "uid": "IQenYZd4k",
  "version": 1,
  "weekStart": ""
}